CHANGELOG.txt
LICENCE.txt
MANIFEST.in
README.txt
setup.py
FtPackage.egg-info/PKG-INFO
FtPackage.egg-info/SOURCES.txt
FtPackage.egg-info/dependency_links.txt
FtPackage.egg-info/entry_points.txt
FtPackage.egg-info/requires.txt
FtPackage.egg-info/top_level.txt
sam/Main.py
sam/__init__.py