Metadata-Version: 1.1
Name: FtPackage
Version: 0.0.4
Summary: built-in python functions
Home-page: UNKNOWN
Author: Punya Keerthi
Author-email: UNKNOWN
License: MIT
Keywords: built-in
Platform: UNKNOWN
Classifier: Development Status :: 5 - Production/Stable
Classifier: Intended Audience :: Education
Classifier: Operating System :: Microsoft :: Windows :: Windows 10
Classifier: License :: OSI Approved :: MIT License
Classifier: Programming Language :: Python :: 3
